[
    {
        "publicationNumber": "10651575",
        "doi": "10.1109/CNNA60945.2023.10652769",
        "publicationYear": "2023",
        "publicationDate": "28-30 Sept. 2023",
        "articleNumber": "10652769",
        "articleTitle": "Intelligent Client Selection for Federated Learning Using Cellular Automata",
        "volume": null,
        "issue": null,
        "startPage": "1",
        "endPage": "4",
        "publisher": "IEEE",
        "articleContentType": "Conferences",
        "publicationTitle": "2023 18th International Workshop on Cellular Nanoscale Networks and their Applications (CNNA)",
        "authors": [
            {
                "id": 37090074412,
                "preferredName": "Nikolaos Pavlidis",
                "firstName": "Nikolaos",
                "lastName": "Pavlidis"
            },
            {
                "id": 37090076882,
                "preferredName": "Vasileios Perifanis",
                "firstName": "Vasileios",
                "lastName": "Perifanis"
            },
            {
                "id": 37088922044,
                "preferredName": "Theodoros Panagiotis Chatzinikolaou",
                "firstName": "Theodoros Panagiotis",
                "lastName": "Chatzinikolaou"
            },
            {
                "id": 37304018300,
                "preferredName": "Georgios Ch. Sirakoulis",
                "firstName": "Georgios Ch.",
                "lastName": "Sirakoulis"
            },
            {
                "id": 37697691600,
                "preferredName": "Pavlos S. Efraimidis",
                "firstName": "Pavlos S.",
                "lastName": "Efraimidis"
            }
        ]
    },
    {
        "publicationNumber": "10651575",
        "doi": "10.1109/CNNA60945.2023.10652671",
        "publicationYear": "2023",
        "publicationDate": "28-30 Sept. 2023",
        "articleNumber": "10652671",
        "articleTitle": "LTSPICE Memristor Neuron with MOS Transistor-Based Logarithmic-Sigmoidal Activation Function",
        "volume": null,
        "issue": null,
        "startPage": "1",
        "endPage": "4",
        "publisher": "IEEE",
        "articleContentType": "Conferences",
        "publicationTitle": "2023 18th International Workshop on Cellular Nanoscale Networks and their Applications (CNNA)",
        "authors": [
            {
                "id": 37297885200,
                "preferredName": "Valeri Mladenov",
                "firstName": "Valeri",
                "lastName": "Mladenov"
            },
            {
                "id": 37297882300,
                "preferredName": "Georgi Tsenov",
                "firstName": "Georgi",
                "lastName": "Tsenov"
            },
            {
                "id": 37086392885,
                "preferredName": "Stoyan Kirilov",
                "firstName": "Stoyan",
                "lastName": "Kirilov"
            }
        ]
    },
    {
        "publicationNumber": "10651575",
        "doi": "10.1109/CNNA60945.2023.10652719",
        "publicationYear": "2023",
        "publicationDate": "28-30 Sept. 2023",
        "articleNumber": "10652719",
        "articleTitle": "An Algorithmic Approach to the Design of a Comprehensive ReRAM Memory Controller",
        "volume": null,
        "issue": null,
        "startPage": "1",
        "endPage": "2",
        "publisher": "IEEE",
        "articleContentType": "Conferences",
        "publicationTitle": "2023 18th International Workshop on Cellular Nanoscale Networks and their Applications (CNNA)",
        "authors": [
            {
                "id": 37088922826,
                "preferredName": "Jose Cayo",
                "firstName": "Jose",
                "lastName": "Cayo"
            },
            {
                "id": 37888434500,
                "preferredName": "Ioannis Vourkas",
                "firstName": "Ioannis",
                "lastName": "Vourkas"
            }
        ]
    },
    {
        "publicationNumber": "10651575",
        "doi": "10.1109/CNNA60945.2023.10652627",
        "publicationYear": "2023",
        "publicationDate": "28-30 Sept. 2023",
        "articleNumber": "10652627",
        "articleTitle": "Towards Dense Indoor Environmental Sensing with LoraWAN",
        "volume": null,
        "issue": null,
        "startPage": "1",
        "endPage": "5",
        "publisher": "IEEE",
        "articleContentType": "Conferences",
        "publicationTitle": "2023 18th International Workshop on Cellular Nanoscale Networks and their Applications (CNNA)",
        "authors": [
            {
                "id": 38093298100,
                "preferredName": "Eleftheria Katsiri",
                "firstName": "Eleftheria",
                "lastName": "Katsiri"
            },
            {
                "id": 578894693644050,
                "preferredName": "Christos Karasoulas",
                "firstName": "Christos",
                "lastName": "Karasoulas"
            },
            {
                "id": 37590547500,
                "preferredName": "Christoforos Keroglou",
                "firstName": "Christoforos",
                "lastName": "Keroglou"
            }
        ]
    },
    {
        "publicationNumber": "10651575",
        "doi": "10.1109/CNNA60945.2023.10652849",
        "publicationYear": "2023",
        "publicationDate": "28-30 Sept. 2023",
        "articleNumber": "10652849",
        "articleTitle": "Implementation of Reservoir Computers Using Simulated Electrostatically Linked Systems",
        "volume": null,
        "issue": null,
        "startPage": "1",
        "endPage": "3",
        "publisher": "IEEE",
        "articleContentType": "Conferences",
        "publicationTitle": "2023 18th International Workshop on Cellular Nanoscale Networks and their Applications (CNNA)",
        "authors": [
            {
                "id": 37670597000,
                "preferredName": "Stavros G. Stavrinides",
                "firstName": "Stavros G.",
                "lastName": "Stavrinides"
            },
            {
                "id": 162992500885855,
                "preferredName": "Panagiotis Tzounakis",
                "firstName": "Panagiotis",
                "lastName": "Tzounakis"
            },
            {
                "id": 197006101010936,
                "preferredName": "Carol De Benito",
                "firstName": "Carol",
                "lastName": "De Benito"
            },
            {
                "id": 37282666900,
                "preferredName": "Christos Tjortjis",
                "firstName": "Christos",
                "lastName": "Tjortjis"
            },
            {
                "id": 974105063017111,
                "preferredName": "M. Moner Al Chawa",
                "firstName": "M. Moner",
                "lastName": "Al Chawa"
            },
            {
                "id": 37086203090,
                "preferredName": "Ioannis Antoniou",
                "firstName": "Ioannis",
                "lastName": "Antoniou"
            },
            {
                "id": 37275069000,
                "preferredName": "Rodrigo Picos",
                "firstName": "Rodrigo",
                "lastName": "Picos"
            }
        ]
    },
    {
        "publicationNumber": "10651575",
        "doi": "10.1109/CNNA60945.2023.10652784",
        "publicationYear": "2023",
        "publicationDate": "28-30 Sept. 2023",
        "articleNumber": "10652784",
        "articleTitle": "Antenna Based Classification of Posture Positions Using 1T1M Crossbar Arrays",
        "volume": null,
        "issue": null,
        "startPage": "1",
        "endPage": "4",
        "publisher": "IEEE",
        "articleContentType": "Conferences",
        "publicationTitle": "2023 18th International Workshop on Cellular Nanoscale Networks and their Applications (CNNA)",
        "authors": [
            {
                "id": 37086410899,
                "preferredName": "Elizabeth George",
                "firstName": "Elizabeth",
                "lastName": "George"
            },
            {
                "id": 37089644657,
                "preferredName": "Aswani Radhakrishnan",
                "firstName": "Aswani",
                "lastName": "Radhakrishnan"
            },
            {
                "id": 213095517275366,
                "preferredName": "Alex James",
                "firstName": "Alex",
                "lastName": "James"
            }
        ]
    },
    {
        "publicationNumber": "10651575",
        "doi": "10.1109/CNNA60945.2023.10652639",
        "publicationYear": "2023",
        "publicationDate": "28-30 Sept. 2023",
        "articleNumber": "10652639",
        "articleTitle": "Toward Real Time Processing of Radar Signals Detecting Elderly People Fall",
        "volume": null,
        "issue": null,
        "startPage": "1",
        "endPage": "3",
        "publisher": "IEEE",
        "articleContentType": "Conferences",
        "publicationTitle": "2023 18th International Workshop on Cellular Nanoscale Networks and their Applications (CNNA)",
        "authors": [
            {
                "id": 37090067544,
                "preferredName": "Dimitrios Arnaoutoglou",
                "firstName": "Dimitrios",
                "lastName": "Arnaoutoglou"
            },
            {
                "id": 537797887340295,
                "preferredName": "Dimitrios Dedemadis",
                "firstName": "Dimitrios",
                "lastName": "Dedemadis"
            },
            {
                "id": 650934377296485,
                "preferredName": "Sotirios Katsimentes",
                "firstName": "Sotirios",
                "lastName": "Katsimentes"
            },
            {
                "id": 476955481816820,
                "preferredName": "Antigone Aikaterini Kyriakou",
                "firstName": "Antigone Aikaterini",
                "lastName": "Kyriakou"
            },
            {
                "id": 37304018300,
                "preferredName": "Georgios Ch. Sirakoulis",
                "firstName": "Georgios Ch.",
                "lastName": "Sirakoulis"
            },
            {
                "id": 37320002200,
                "preferredName": "George Kyriacou",
                "firstName": "George",
                "lastName": "Kyriacou"
            },
            {
                "id": 37089454975,
                "preferredName": "Athanasios Grekidis",
                "firstName": "Athanasios",
                "lastName": "Grekidis"
            },
            {
                "id": 37085723464,
                "preferredName": "Dimitrios Menychtas",
                "firstName": "Dimitrios",
                "lastName": "Menychtas"
            },
            {
                "id": 37089455534,
                "preferredName": "Nikolaos Aggelousis",
                "firstName": "Nikolaos",
                "lastName": "Aggelousis"
            }
        ]
    },
    {
        "publicationNumber": "10651575",
        "doi": "10.1109/CNNA60945.2023.10652757",
        "publicationYear": "2023",
        "publicationDate": "28-30 Sept. 2023",
        "articleNumber": "10652757",
        "articleTitle": "Analog Unidirectional Memristive and Memcapacitive Device for Neuromorphic Computing",
        "volume": null,
        "issue": null,
        "startPage": "1",
        "endPage": "4",
        "publisher": "IEEE",
        "articleContentType": "Conferences",
        "publicationTitle": "2023 18th International Workshop on Cellular Nanoscale Networks and their Applications (CNNA)",
        "authors": [
            {
                "id": 178704150288107,
                "preferredName": "Muhammad Umair Khan",
                "firstName": "Muhammad Umair",
                "lastName": "Khan"
            },
            {
                "id": 37086004168,
                "preferredName": "Yawar Abbas",
                "firstName": "Yawar",
                "lastName": "Abbas"
            },
            {
                "id": 37574033300,
                "preferredName": "Baker Mohammad",
                "firstName": "Baker",
                "lastName": "Mohammad"
            }
        ]
    },
    {
        "publicationNumber": "10651575",
        "doi": "10.1109/CNNA60945.2023.10652692",
        "publicationYear": "2023",
        "publicationDate": "28-30 Sept. 2023",
        "articleNumber": "10652692",
        "articleTitle": "Towards a Modular Lower Body Robotic Model Using the Product of Exponentials",
        "volume": null,
        "issue": null,
        "startPage": "1",
        "endPage": "3",
        "publisher": "IEEE",
        "articleContentType": "Conferences",
        "publicationTitle": "2023 18th International Workshop on Cellular Nanoscale Networks and their Applications (CNNA)",
        "authors": [
            {
                "id": 37085723464,
                "preferredName": "Dimitrios Menychtas",
                "firstName": "Dimitrios",
                "lastName": "Menychtas"
            },
            {
                "id": 211323671966432,
                "preferredName": "Athanasios Gkrekidis",
                "firstName": "Athanasios",
                "lastName": "Gkrekidis"
            },
            {
                "id": 295494054384062,
                "preferredName": "Georgios Michailidis",
                "firstName": "Georgios",
                "lastName": "Michailidis"
            },
            {
                "id": 120549590799607,
                "preferredName": "Archontissa Kanavaki",
                "firstName": "Archontissa",
                "lastName": "Kanavaki"
            },
            {
                "id": 504185560844834,
                "preferredName": "Evgenia Kouli",
                "firstName": "Evgenia",
                "lastName": "Kouli"
            },
            {
                "id": 656312968958360,
                "preferredName": "Theodoros Tzelepis",
                "firstName": "Theodoros",
                "lastName": "Tzelepis"
            },
            {
                "id": 418703723664427,
                "preferredName": "Panagiotis Kasimatis",
                "firstName": "Panagiotis",
                "lastName": "Kasimatis"
            },
            {
                "id": 839163706119975,
                "preferredName": "Konstantinos Astrapellos",
                "firstName": "Konstantinos",
                "lastName": "Astrapellos"
            },
            {
                "id": 164028666258624,
                "preferredName": "Vassilios Gourgoulis",
                "firstName": "Vassilios",
                "lastName": "Gourgoulis"
            },
            {
                "id": 663463350681173,
                "preferredName": "Ilias Smilios",
                "firstName": "Ilias",
                "lastName": "Smilios"
            },
            {
                "id": 37704903000,
                "preferredName": "Maria Michalopoulou",
                "firstName": "Maria",
                "lastName": "Michalopoulou"
            },
            {
                "id": 953803426932047,
                "preferredName": "Helen T. Douda",
                "firstName": "Helen T.",
                "lastName": "Douda"
            },
            {
                "id": 37304018300,
                "preferredName": "Georgios Ch. Sirakoulis",
                "firstName": "Georgios Ch.",
                "lastName": "Sirakoulis"
            },
            {
                "id": 37089455534,
                "preferredName": "Nikolaos Aggelousis",
                "firstName": "Nikolaos",
                "lastName": "Aggelousis"
            }
        ]
    },
    {
        "publicationNumber": "10651575",
        "doi": "10.1109/CNNA60945.2023.10652618",
        "publicationYear": "2023",
        "publicationDate": "28-30 Sept. 2023",
        "articleNumber": "10652618",
        "articleTitle": "Action Recognition via Graph Convolutional Networks for the Assisted Living of the Elderly",
        "volume": null,
        "issue": null,
        "startPage": "1",
        "endPage": "4",
        "publisher": "IEEE",
        "articleContentType": "Conferences",
        "publicationTitle": "2023 18th International Workshop on Cellular Nanoscale Networks and their Applications (CNNA)",
        "authors": [
            {
                "id": 37090066940,
                "preferredName": "Zois Tsakiris",
                "firstName": "Zois",
                "lastName": "Tsakiris"
            },
            {
                "id": 37085585351,
                "preferredName": "Lazaros Tsochatzidis",
                "firstName": "Lazaros",
                "lastName": "Tsochatzidis"
            },
            {
                "id": 37869410200,
                "preferredName": "Ioannis Pratikakis",
                "firstName": "Ioannis",
                "lastName": "Pratikakis"
            },
            {
                "id": 37085723464,
                "preferredName": "Dimitrios Menychtas",
                "firstName": "Dimitrios",
                "lastName": "Menychtas"
            },
            {
                "id": 37089455534,
                "preferredName": "Nikolaos Aggelousis",
                "firstName": "Nikolaos",
                "lastName": "Aggelousis"
            }
        ]
    },
    {
        "publicationNumber": "10651575",
        "doi": "10.1109/CNNA60945.2023.10652765",
        "publicationYear": "2023",
        "publicationDate": "28-30 Sept. 2023",
        "articleNumber": "10652765",
        "articleTitle": "A 93nW, Analog, Parallel-Connected Threshold Classifier for Epileptic Seizure Prediction",
        "volume": null,
        "issue": null,
        "startPage": "1",
        "endPage": "4",
        "publisher": "IEEE",
        "articleContentType": "Conferences",
        "publicationTitle": "2023 18th International Workshop on Cellular Nanoscale Networks and their Applications (CNNA)",
        "authors": [
            {
                "id": 37086596285,
                "preferredName": "Vassilis Alimisis",
                "firstName": "Vassilis",
                "lastName": "Alimisis"
            },
            {
                "id": 37089911171,
                "preferredName": "Argyro Kamperi",
                "firstName": "Argyro",
                "lastName": "Kamperi"
            },
            {
                "id": 701749191724488,
                "preferredName": "Nikolaos P. Eleftheriou",
                "firstName": "Nikolaos P.",
                "lastName": "Eleftheriou"
            },
            {
                "id": 37299944100,
                "preferredName": "Paul P. Sotiriadis",
                "firstName": "Paul P.",
                "lastName": "Sotiriadis"
            }
        ]
    },
    {
        "publicationNumber": "10651575",
        "doi": "10.1109/CNNA60945.2023.10652838",
        "publicationYear": "2023",
        "publicationDate": "28-30 Sept. 2023",
        "articleNumber": "10652838",
        "articleTitle": "Memristive Stochastic Binary Neurons for Solving Optimisation Problems",
        "volume": null,
        "issue": null,
        "startPage": "1",
        "endPage": "5",
        "publisher": "IEEE",
        "articleContentType": "Conferences",
        "publicationTitle": "2023 18th International Workshop on Cellular Nanoscale Networks and their Applications (CNNA)",
        "authors": [
            {
                "id": 37089235860,
                "preferredName": "Adil Malik",
                "firstName": "Adil",
                "lastName": "Malik"
            },
            {
                "id": 37270084500,
                "preferredName": "Christos Papavassiliou",
                "firstName": "Christos",
                "lastName": "Papavassiliou"
            }
        ]
    },
    {
        "publicationNumber": "10651575",
        "doi": "10.1109/CNNA60945.2023.10652842",
        "publicationYear": "2023",
        "publicationDate": "28-30 Sept. 2023",
        "articleNumber": "10652842",
        "articleTitle": "Interdisciplinary Applications of Non-Integer Order Circuits & Systems",
        "volume": null,
        "issue": null,
        "startPage": "1",
        "endPage": "4",
        "publisher": "IEEE",
        "articleContentType": "Conferences",
        "publicationTitle": "2023 18th International Workshop on Cellular Nanoscale Networks and their Applications (CNNA)",
        "authors": [
            {
                "id": 37088951711,
                "preferredName": "Julia Nako",
                "firstName": "Julia",
                "lastName": "Nako"
            },
            {
                "id": 37086124537,
                "preferredName": "Stavroula Kapoulea",
                "firstName": "Stavroula",
                "lastName": "Kapoulea"
            },
            {
                "id": 37086318515,
                "preferredName": "Panagiotis Bertsias",
                "firstName": "Panagiotis",
                "lastName": "Bertsias"
            },
            {
                "id": 37085583624,
                "preferredName": "Georgia Tsirimokou",
                "firstName": "Georgia",
                "lastName": "Tsirimokou"
            },
            {
                "id": 37269370500,
                "preferredName": "Costas Psychalinos",
                "firstName": "Costas",
                "lastName": "Psychalinos"
            }
        ]
    },
    {
        "publicationNumber": "10651575",
        "doi": "10.1109/CNNA60945.2023.10652632",
        "publicationYear": "2023",
        "publicationDate": "28-30 Sept. 2023",
        "articleNumber": "10652632",
        "articleTitle": "Effects of a Group Exercise on the Center of Mass of Elderly People with a High Risk of Falling",
        "volume": null,
        "issue": null,
        "startPage": "1",
        "endPage": "3",
        "publisher": "IEEE",
        "articleContentType": "Conferences",
        "publicationTitle": "2023 18th International Workshop on Cellular Nanoscale Networks and their Applications (CNNA)",
        "authors": [
            {
                "id": 37085723464,
                "preferredName": "Dimitrios Menychtas",
                "firstName": "Dimitrios",
                "lastName": "Menychtas"
            },
            {
                "id": 504185560844834,
                "preferredName": "Evgenia Kouli",
                "firstName": "Evgenia",
                "lastName": "Kouli"
            },
            {
                "id": 211323671966432,
                "preferredName": "Athanasios Gkrekidis",
                "firstName": "Athanasios",
                "lastName": "Gkrekidis"
            },
            {
                "id": 120549590799607,
                "preferredName": "Archontissa Kanavaki",
                "firstName": "Archontissa",
                "lastName": "Kanavaki"
            },
            {
                "id": 345064922951763,
                "preferredName": "Stefania Pavlidou",
                "firstName": "Stefania",
                "lastName": "Pavlidou"
            },
            {
                "id": 298167166056713,
                "preferredName": "Elpiniki Nasiou",
                "firstName": "Elpiniki",
                "lastName": "Nasiou"
            },
            {
                "id": 651318680290508,
                "preferredName": "Evangelia Abrasi",
                "firstName": "Evangelia",
                "lastName": "Abrasi"
            },
            {
                "id": 850636301378734,
                "preferredName": "Georgios Kontogiannis",
                "firstName": "Georgios",
                "lastName": "Kontogiannis"
            },
            {
                "id": 953803426932047,
                "preferredName": "Helen T. Douda",
                "firstName": "Helen T.",
                "lastName": "Douda"
            },
            {
                "id": 37704903000,
                "preferredName": "Maria Michalopoulou",
                "firstName": "Maria",
                "lastName": "Michalopoulou"
            },
            {
                "id": 663463350681173,
                "preferredName": "Ilias Smilios",
                "firstName": "Ilias",
                "lastName": "Smilios"
            },
            {
                "id": 164028666258624,
                "preferredName": "Vassilios Gourgoulis",
                "firstName": "Vassilios",
                "lastName": "Gourgoulis"
            },
            {
                "id": 37304018300,
                "preferredName": "Georgios Ch. Sirakoulis",
                "firstName": "Georgios Ch.",
                "lastName": "Sirakoulis"
            },
            {
                "id": 37089455534,
                "preferredName": "Nikolaos Aggelousis",
                "firstName": "Nikolaos",
                "lastName": "Aggelousis"
            }
        ]
    },
    {
        "publicationNumber": "10651575",
        "doi": "10.1109/CNNA60945.2023.10652775",
        "publicationYear": "2023",
        "publicationDate": "28-30 Sept. 2023",
        "articleNumber": "10652775",
        "articleTitle": "Historical Document Image Binarization Using a Lightweight U-Net Derivative Architecture",
        "volume": null,
        "issue": null,
        "startPage": "1",
        "endPage": "5",
        "publisher": "IEEE",
        "articleContentType": "Conferences",
        "publicationTitle": "2023 18th International Workshop on Cellular Nanoscale Networks and their Applications (CNNA)",
        "authors": [
            {
                "id": 400244796917562,
                "preferredName": "Nikolaos Detsikas",
                "firstName": "Nikolaos",
                "lastName": "Detsikas"
            },
            {
                "id": 37296977800,
                "preferredName": "Nikolaos Mitianoudis",
                "firstName": "Nikolaos",
                "lastName": "Mitianoudis"
            }
        ]
    },
    {
        "publicationNumber": "10651575",
        "doi": "10.1109/CNNA60945.2023.10652669",
        "publicationYear": "2023",
        "publicationDate": "28-30 Sept. 2023",
        "articleNumber": "10652669",
        "articleTitle": "Older Adults' Views on the use of In-Home Ambient Sensors and Assistive Robotic Agents in Greece. Data from the ASPiDA Project",
        "volume": null,
        "issue": null,
        "startPage": "1",
        "endPage": "4",
        "publisher": "IEEE",
        "articleContentType": "Conferences",
        "publicationTitle": "2023 18th International Workshop on Cellular Nanoscale Networks and their Applications (CNNA)",
        "authors": [
            {
                "id": 120549590799607,
                "preferredName": "Archontissa Kanavaki",
                "firstName": "Archontissa",
                "lastName": "Kanavaki"
            },
            {
                "id": 37088760414,
                "preferredName": "Ioannis Kansizoglou",
                "firstName": "Ioannis",
                "lastName": "Kansizoglou"
            },
            {
                "id": 37704903000,
                "preferredName": "Maria Michalopoulou",
                "firstName": "Maria",
                "lastName": "Michalopoulou"
            },
            {
                "id": 37304018300,
                "preferredName": "Georgios Ch. Sirakoulis",
                "firstName": "Georgios Ch.",
                "lastName": "Sirakoulis"
            },
            {
                "id": 211323671966432,
                "preferredName": "Athanasios Gkrekidis",
                "firstName": "Athanasios",
                "lastName": "Gkrekidis"
            },
            {
                "id": 504185560844834,
                "preferredName": "Evgenia Kouli",
                "firstName": "Evgenia",
                "lastName": "Kouli"
            },
            {
                "id": 37085723464,
                "preferredName": "Dimitrios Menychtas",
                "firstName": "Dimitrios",
                "lastName": "Menychtas"
            },
            {
                "id": 199710236988015,
                "preferredName": "Helen Douda",
                "firstName": "Helen",
                "lastName": "Douda"
            },
            {
                "id": 663463350681173,
                "preferredName": "Ilias Smilios",
                "firstName": "Ilias",
                "lastName": "Smilios"
            },
            {
                "id": 164028666258624,
                "preferredName": "Vassilios Gourgoulis",
                "firstName": "Vassilios",
                "lastName": "Gourgoulis"
            },
            {
                "id": 37303793300,
                "preferredName": "Antonios Gasteratos",
                "firstName": "Antonios",
                "lastName": "Gasteratos"
            },
            {
                "id": 37089455534,
                "preferredName": "Nikolaos Aggelousis",
                "firstName": "Nikolaos",
                "lastName": "Aggelousis"
            }
        ]
    },
    {
        "publicationNumber": "10651575",
        "doi": "10.1109/CNNA60945.2023.10652783",
        "publicationYear": "2023",
        "publicationDate": "28-30 Sept. 2023",
        "articleNumber": "10652783",
        "articleTitle": "Variability Reduction with Bilayer RRAM Device",
        "volume": null,
        "issue": null,
        "startPage": "1",
        "endPage": "4",
        "publisher": "IEEE",
        "articleContentType": "Conferences",
        "publicationTitle": "2023 18th International Workshop on Cellular Nanoscale Networks and their Applications (CNNA)",
        "authors": [
            {
                "id": 37088877279,
                "preferredName": "Tim Kempen",
                "firstName": "Tim",
                "lastName": "Kempen"
            },
            {
                "id": 893313739186656,
                "preferredName": "Ankit Bende",
                "firstName": "Ankit",
                "lastName": "Bende"
            },
            {
                "id": 904427917442195,
                "preferredName": "Alexandros Sarantopoulos",
                "firstName": "Alexandros",
                "lastName": "Sarantopoulos"
            },
            {
                "id": 524452078311962,
                "preferredName": "Regina Dittmann",
                "firstName": "Regina",
                "lastName": "Dittmann"
            },
            {
                "id": 37088512482,
                "preferredName": "Christopher Bengel",
                "firstName": "Christopher",
                "lastName": "Bengel"
            },
            {
                "id": 37086432084,
                "preferredName": "André Zambanini",
                "firstName": "André",
                "lastName": "Zambanini"
            },
            {
                "id": 370033341909976,
                "preferredName": "Dennis Nielinger",
                "firstName": "Dennis",
                "lastName": "Nielinger"
            },
            {
                "id": 145059470426381,
                "preferredName": "Stephan Menzel",
                "firstName": "Stephan",
                "lastName": "Menzel"
            },
            {
                "id": 37089187452,
                "preferredName": "Vikas Rana",
                "firstName": "Vikas",
                "lastName": "Rana"
            }
        ]
    },
    {
        "publicationNumber": "10651575",
        "doi": "10.1109/CNNA60945.2023.10652823",
        "publicationYear": "2023",
        "publicationDate": "28-30 Sept. 2023",
        "articleNumber": "10652823",
        "articleTitle": "Design of Approximate DNN Accelerators through Framework-Based and Circuit-Level Techniques",
        "volume": null,
        "issue": null,
        "startPage": "1",
        "endPage": "4",
        "publisher": "IEEE",
        "articleContentType": "Conferences",
        "publicationTitle": "2023 18th International Workshop on Cellular Nanoscale Networks and their Applications (CNNA)",
        "authors": [
            {
                "id": 37086278407,
                "preferredName": "Vasileios Leon",
                "firstName": "Vasileios",
                "lastName": "Leon"
            },
            {
                "id": 37391631000,
                "preferredName": "Sotirios Xydis",
                "firstName": "Sotirios",
                "lastName": "Xydis"
            },
            {
                "id": 37402259700,
                "preferredName": "George Lentaris",
                "firstName": "George",
                "lastName": "Lentaris"
            },
            {
                "id": 37271305000,
                "preferredName": "Dimitrios Soudris",
                "firstName": "Dimitrios",
                "lastName": "Soudris"
            }
        ]
    },
    {
        "publicationNumber": "10651575",
        "doi": "10.1109/CNNA60945.2023.10652717",
        "publicationYear": "2023",
        "publicationDate": "28-30 Sept. 2023",
        "articleNumber": "10652717",
        "articleTitle": "Enabling Real-Time Network Intrusion Detection Through Custom Hardware Architecture",
        "volume": null,
        "issue": null,
        "startPage": "1",
        "endPage": "2",
        "publisher": "IEEE",
        "articleContentType": "Conferences",
        "publicationTitle": "2023 18th International Workshop on Cellular Nanoscale Networks and their Applications (CNNA)",
        "authors": [
            {
                "id": 37086391827,
                "preferredName": "Dimitrios Danopoulos",
                "firstName": "Dimitrios",
                "lastName": "Danopoulos"
            },
            {
                "id": 37271305000,
                "preferredName": "Dimitrios Soudris",
                "firstName": "Dimitrios",
                "lastName": "Soudris"
            }
        ]
    },
    {
        "publicationNumber": "10651575",
        "doi": "10.1109/CNNA60945.2023.10652864",
        "publicationYear": "2023",
        "publicationDate": "28-30 Sept. 2023",
        "articleNumber": "10652864",
        "articleTitle": "Investigation of Proteinoid Microspheres for Cellular Nanonetworks Based on Frequency Response",
        "volume": null,
        "issue": null,
        "startPage": "1",
        "endPage": "5",
        "publisher": "IEEE",
        "articleContentType": "Conferences",
        "publicationTitle": "2023 18th International Workshop on Cellular Nanoscale Networks and their Applications (CNNA)",
        "authors": [
            {
                "id": 944785575927961,
                "preferredName": "Panagiotis Mougkogiannis",
                "firstName": "Panagiotis",
                "lastName": "Mougkogiannis"
            },
            {
                "id": 38306776100,
                "preferredName": "Andrew Adamatzky",
                "firstName": "Andrew",
                "lastName": "Adamatzky"
            }
        ]
    },
    {
        "publicationNumber": "10651575",
        "doi": "10.1109/CNNA60945.2023.10652621",
        "publicationYear": "2023",
        "publicationDate": "28-30 Sept. 2023",
        "articleNumber": "10652621",
        "articleTitle": "Performance Analysis of Unipolar CBRAM in 1D1R Configuration Towards IMC Under Realistic Conditions",
        "volume": null,
        "issue": null,
        "startPage": "1",
        "endPage": "6",
        "publisher": "IEEE",
        "articleContentType": "Conferences",
        "publicationTitle": "2023 18th International Workshop on Cellular Nanoscale Networks and their Applications (CNNA)",
        "authors": [
            {
                "id": 346955686697400,
                "preferredName": "Ioannis Tompris",
                "firstName": "Ioannis",
                "lastName": "Tompris"
            },
            {
                "id": 37089693990,
                "preferredName": "Evangelos Tsipas",
                "firstName": "Evangelos",
                "lastName": "Tsipas"
            },
            {
                "id": 37086498186,
                "preferredName": "Iosif-Angelos Fyrigos",
                "firstName": "Iosif-Angelos",
                "lastName": "Fyrigos"
            },
            {
                "id": 37304018300,
                "preferredName": "Georgios Ch. Sirakoulis",
                "firstName": "Georgios Ch.",
                "lastName": "Sirakoulis"
            }
        ]
    },
    {
        "publicationNumber": "10651575",
        "doi": "10.1109/CNNA60945.2023.10652656",
        "publicationYear": "2023",
        "publicationDate": "28-30 Sept. 2023",
        "articleNumber": "10652656",
        "articleTitle": "Approximate Parallel Annealing Ising Machines (APAIMs): Controller and Arithmetic Design",
        "volume": null,
        "issue": null,
        "startPage": "1",
        "endPage": "5",
        "publisher": "IEEE",
        "articleContentType": "Conferences",
        "publicationTitle": "2023 18th International Workshop on Cellular Nanoscale Networks and their Applications (CNNA)",
        "authors": [
            {
                "id": 37089162791,
                "preferredName": "Qichao Tao",
                "firstName": "Qichao",
                "lastName": "Tao"
            },
            {
                "id": 37086498609,
                "preferredName": "Tingting Zhang",
                "firstName": "Tingting",
                "lastName": "Zhang"
            },
            {
                "id": 37556260600,
                "preferredName": "Jie Han",
                "firstName": "Jie",
                "lastName": "Han"
            }
        ]
    },
    {
        "publicationNumber": "10651575",
        "doi": "10.1109/CNNA60945.2023.10652835",
        "publicationYear": "2023",
        "publicationDate": "28-30 Sept. 2023",
        "articleNumber": "10652835",
        "articleTitle": "Enhancing the A* Algorithm for Efficient Route Planning of Agriculture",
        "volume": null,
        "issue": null,
        "startPage": "1",
        "endPage": "4",
        "publisher": "IEEE",
        "articleContentType": "Conferences",
        "publicationTitle": "2023 18th International Workshop on Cellular Nanoscale Networks and their Applications (CNNA)",
        "authors": [
            {
                "id": 37089001354,
                "preferredName": "Antonios Chatzisavvas",
                "firstName": "Antonios",
                "lastName": "Chatzisavvas"
            },
            {
                "id": 37266184300,
                "preferredName": "Malamati Louta",
                "firstName": "Malamati",
                "lastName": "Louta"
            },
            {
                "id": 37328217200,
                "preferredName": "Minas Dasygenis",
                "firstName": "Minas",
                "lastName": "Dasygenis"
            }
        ]
    },
    {
        "publicationNumber": "10651575",
        "doi": "10.1109/CNNA60945.2023.10652731",
        "publicationYear": "2023",
        "publicationDate": "28-30 Sept. 2023",
        "articleNumber": "10652731",
        "articleTitle": "Preliminary Study on Charging Patterns Dedicated for Low Power Smart Mobile Devices Via Modular RF Energy Harvester: iPowerKit",
        "volume": null,
        "issue": null,
        "startPage": "1",
        "endPage": "5",
        "publisher": "IEEE",
        "articleContentType": "Conferences",
        "publicationTitle": "2023 18th International Workshop on Cellular Nanoscale Networks and their Applications (CNNA)",
        "authors": [
            {
                "id": 37086066210,
                "preferredName": "Alexandros Boubaris",
                "firstName": "Alexandros",
                "lastName": "Boubaris"
            },
            {
                "id": 37085590396,
                "preferredName": "Nick Papanikolaou",
                "firstName": "Nick",
                "lastName": "Papanikolaou"
            },
            {
                "id": 312024309329475,
                "preferredName": "Christos Christodoulou",
                "firstName": "Christos",
                "lastName": "Christodoulou"
            }
        ]
    },
    {
        "publicationNumber": "10651575",
        "doi": "10.1109/CNNA60945.2023.10652619",
        "publicationYear": "2023",
        "publicationDate": "28-30 Sept. 2023",
        "articleNumber": "10652619",
        "articleTitle": "The Case for Asymmetric Systolic Array Floorplanning",
        "volume": null,
        "issue": null,
        "startPage": "1",
        "endPage": "4",
        "publisher": "IEEE",
        "articleContentType": "Conferences",
        "publicationTitle": "2023 18th International Workshop on Cellular Nanoscale Networks and their Applications (CNNA)",
        "authors": [
            {
                "id": 37089565409,
                "preferredName": "Christodoulos Peltekis",
                "firstName": "Christodoulos",
                "lastName": "Peltekis"
            },
            {
                "id": 37089285850,
                "preferredName": "Dionysios Filippas",
                "firstName": "Dionysios",
                "lastName": "Filippas"
            },
            {
                "id": 777681490858818,
                "preferredName": "Giorgos Dimitrakopoulos",
                "firstName": "Giorgos",
                "lastName": "Dimitrakopoulos"
            },
            {
                "id": 37300402600,
                "preferredName": "Chrysostomos Nicopoulos",
                "firstName": "Chrysostomos",
                "lastName": "Nicopoulos"
            }
        ]
    },
    {
        "publicationNumber": "10651575",
        "doi": "10.1109/CNNA60945.2023.10652766",
        "publicationYear": "2023",
        "publicationDate": "28-30 Sept. 2023",
        "articleNumber": "10652766",
        "articleTitle": "A Memristive Neuromorphic Voltage-to-Frequency Mapping Oscillator for Automotive Applications",
        "volume": null,
        "issue": null,
        "startPage": "1",
        "endPage": "4",
        "publisher": "IEEE",
        "articleContentType": "Conferences",
        "publicationTitle": "2023 18th International Workshop on Cellular Nanoscale Networks and their Applications (CNNA)",
        "authors": [
            {
                "id": 37089826019,
                "preferredName": "Ioannis K. Chatzipaschalis",
                "firstName": "Ioannis K.",
                "lastName": "Chatzipaschalis"
            },
            {
                "id": 37088922044,
                "preferredName": "Theodoros Panagiotis Chatzinikolaou",
                "firstName": "Theodoros Panagiotis",
                "lastName": "Chatzinikolaou"
            },
            {
                "id": 37086498186,
                "preferredName": "Iosif-Angelos Fyrigos",
                "firstName": "Iosif-Angelos",
                "lastName": "Fyrigos"
            },
            {
                "id": 556496778753329,
                "preferredName": "Antonio Rubio",
                "firstName": "Antonio",
                "lastName": "Rubio"
            },
            {
                "id": 37304018300,
                "preferredName": "Georgios Ch. Sirakoulis",
                "firstName": "Georgios Ch.",
                "lastName": "Sirakoulis"
            }
        ]
    },
    {
        "publicationNumber": "10651575",
        "doi": "10.1109/CNNA60945.2023.10652658",
        "publicationYear": "2023",
        "publicationDate": "28-30 Sept. 2023",
        "articleNumber": "10652658",
        "articleTitle": "Stable Diffusion with Continuous-time Neural Networks",
        "volume": null,
        "issue": null,
        "startPage": "1",
        "endPage": "4",
        "publisher": "IEEE",
        "articleContentType": "Conferences",
        "publicationTitle": "2023 18th International Workshop on Cellular Nanoscale Networks and their Applications (CNNA)",
        "authors": [
            {
                "id": 37393811800,
                "preferredName": "Andras Horvath",
                "firstName": "Andras",
                "lastName": "Horvath"
            }
        ]
    },
    {
        "publicationNumber": "10651575",
        "doi": "10.1109/CNNA60945.2023.10652729",
        "publicationYear": "2023",
        "publicationDate": "28-30 Sept. 2023",
        "articleNumber": "10652729",
        "articleTitle": "Contactless Blood Pressure Estimation Using Infrared Video from Facial and Hand Regions",
        "volume": null,
        "issue": null,
        "startPage": "1",
        "endPage": "5",
        "publisher": "IEEE",
        "articleContentType": "Conferences",
        "publicationTitle": "2023 18th International Workshop on Cellular Nanoscale Networks and their Applications (CNNA)",
        "authors": [
            {
                "id": 37090052143,
                "preferredName": "Thomas Stogiannopoulos",
                "firstName": "Thomas",
                "lastName": "Stogiannopoulos"
            },
            {
                "id": 37296977800,
                "preferredName": "Nikolaos Mitianoudis",
                "firstName": "Nikolaos",
                "lastName": "Mitianoudis"
            }
        ]
    },
    {
        "publicationNumber": "10651575",
        "doi": "10.1109/CNNA60945.2023.10652808",
        "publicationYear": "2023",
        "publicationDate": "28-30 Sept. 2023",
        "articleNumber": "10652808",
        "articleTitle": "Navigation with Care: The ASPiDA Assistive Robot",
        "volume": null,
        "issue": null,
        "startPage": "1",
        "endPage": "4",
        "publisher": "IEEE",
        "articleContentType": "Conferences",
        "publicationTitle": "2023 18th International Workshop on Cellular Nanoscale Networks and their Applications (CNNA)",
        "authors": [
            {
                "id": 37089454827,
                "preferredName": "Katerina Maria Oikonomou",
                "firstName": "Katerina Maria",
                "lastName": "Oikonomou"
            },
            {
                "id": 37088524584,
                "preferredName": "Ioannis Tsampikos Papapetros",
                "firstName": "Ioannis Tsampikos",
                "lastName": "Papapetros"
            },
            {
                "id": 37088760414,
                "preferredName": "Ioannis Kansizoglou",
                "firstName": "Ioannis",
                "lastName": "Kansizoglou"
            },
            {
                "id": 37304018300,
                "preferredName": "Georgios Ch. Sirakoulis",
                "firstName": "Georgios Ch.",
                "lastName": "Sirakoulis"
            },
            {
                "id": 37303793300,
                "preferredName": "Antonios Gasteratos",
                "firstName": "Antonios",
                "lastName": "Gasteratos"
            }
        ]
    },
    {
        "publicationNumber": "10651575",
        "doi": "10.1109/CNNA60945.2023.10652743",
        "publicationYear": "2023",
        "publicationDate": "28-30 Sept. 2023",
        "articleNumber": "10652743",
        "articleTitle": "Employing Vector Field Techniques on the Analysis of Memristor Cellular Nonlinear Networks Cell Dynamics",
        "volume": null,
        "issue": null,
        "startPage": "1",
        "endPage": "4",
        "publisher": "IEEE",
        "articleContentType": "Conferences",
        "publicationTitle": "2023 18th International Workshop on Cellular Nanoscale Networks and their Applications (CNNA)",
        "authors": [
            {
                "id": 37086854100,
                "preferredName": "Chandan Singh",
                "firstName": "Chandan",
                "lastName": "Singh"
            },
            {
                "id": 37085340720,
                "preferredName": "Vasileios Ntinas",
                "firstName": "Vasileios",
                "lastName": "Ntinas"
            },
            {
                "id": 506618966096800,
                "preferredName": "Dimitrios Prousalis",
                "firstName": "Dimitrios",
                "lastName": "Prousalis"
            },
            {
                "id": 37089375436,
                "preferredName": "Yongmin Wang",
                "firstName": "Yongmin",
                "lastName": "Wang"
            },
            {
                "id": 37085695434,
                "preferredName": "Ahmet Samil Demirkol",
                "firstName": "Ahmet Samil",
                "lastName": "Demirkol"
            },
            {
                "id": 557777751680281,
                "preferredName": "Ioannis Messaris",
                "firstName": "Ioannis",
                "lastName": "Messaris"
            },
            {
                "id": 37089187452,
                "preferredName": "Vikas Rana",
                "firstName": "Vikas",
                "lastName": "Rana"
            },
            {
                "id": 145059470426381,
                "preferredName": "Stephan Menzel",
                "firstName": "Stephan",
                "lastName": "Menzel"
            },
            {
                "id": 218349681823240,
                "preferredName": "Alon Ascoli",
                "firstName": "Alon",
                "lastName": "Ascoli"
            },
            {
                "id": 258908827049055,
                "preferredName": "Ronald Tetzlaff",
                "firstName": "Ronald",
                "lastName": "Tetzlaff"
            }
        ]
    },
    {
        "publicationNumber": "10651575",
        "doi": "10.1109/CNNA60945.2023.10652778",
        "publicationYear": "2023",
        "publicationDate": "28-30 Sept. 2023",
        "articleNumber": "10652778",
        "articleTitle": "On the Design of Oscillatory Circuits Based on Stanford Memristor Model",
        "volume": null,
        "issue": null,
        "startPage": "1",
        "endPage": "4",
        "publisher": "IEEE",
        "articleContentType": "Conferences",
        "publicationTitle": "2023 18th International Workshop on Cellular Nanoscale Networks and their Applications (CNNA)",
        "authors": [
            {
                "id": 37270739400,
                "preferredName": "Mauro Di Marco",
                "firstName": "Mauro",
                "lastName": "Di Marco"
            },
            {
                "id": 37270735600,
                "preferredName": "Mauro Forti",
                "firstName": "Mauro",
                "lastName": "Forti"
            },
            {
                "id": 37267334700,
                "preferredName": "Luca Pancioni",
                "firstName": "Luca",
                "lastName": "Pancioni"
            },
            {
                "id": 37391089200,
                "preferredName": "Giacomo Innocenti",
                "firstName": "Giacomo",
                "lastName": "Innocenti"
            },
            {
                "id": 37270737200,
                "preferredName": "Alberto Tesi",
                "firstName": "Alberto",
                "lastName": "Tesi"
            }
        ]
    },
    {
        "publicationNumber": "10651575",
        "doi": "10.1109/CNNA60945.2023.10652706",
        "publicationYear": "2023",
        "publicationDate": "28-30 Sept. 2023",
        "articleNumber": "10652706",
        "articleTitle": "Trading Parallelism for Resources in the FPGA Implementation of Cellular Automata-Based Models",
        "volume": null,
        "issue": null,
        "startPage": "1",
        "endPage": "4",
        "publisher": "IEEE",
        "articleContentType": "Conferences",
        "publicationTitle": "2023 18th International Workshop on Cellular Nanoscale Networks and their Applications (CNNA)",
        "authors": [
            {
                "id": 572781574768264,
                "preferredName": "Kevin Pizarro",
                "firstName": "Kevin",
                "lastName": "Pizarro"
            },
            {
                "id": 307842928845777,
                "preferredName": "Miguel Andrade",
                "firstName": "Miguel",
                "lastName": "Andrade"
            },
            {
                "id": 37888434500,
                "preferredName": "Ioannis Vourkas",
                "firstName": "Ioannis",
                "lastName": "Vourkas"
            }
        ]
    },
    {
        "publicationNumber": "10651575",
        "doi": "10.1109/CNNA60945.2023.10652852",
        "publicationYear": "2023",
        "publicationDate": "28-30 Sept. 2023",
        "articleNumber": "10652852",
        "articleTitle": "Explaining a Recent Observation of Bistability in the Oscillatory Response of a Pulse-Driven ReRAM",
        "volume": null,
        "issue": null,
        "startPage": "1",
        "endPage": "6",
        "publisher": "IEEE",
        "articleContentType": "Conferences",
        "publicationTitle": "2023 18th International Workshop on Cellular Nanoscale Networks and their Applications (CNNA)",
        "authors": [
            {
                "id": 594659946274162,
                "preferredName": "A. Ascoli",
                "firstName": "A.",
                "lastName": "Ascoli"
            },
            {
                "id": 37089629047,
                "preferredName": "N. Schmitt",
                "firstName": "N.",
                "lastName": "Schmitt"
            },
            {
                "id": 804028671032945,
                "preferredName": "I. Messaris",
                "firstName": "I.",
                "lastName": "Messaris"
            },
            {
                "id": 381807506131583,
                "preferredName": "A.S. Demirkol",
                "firstName": "A.S.",
                "lastName": "Demirkol"
            },
            {
                "id": 558219195778751,
                "preferredName": "V. Ntinas",
                "firstName": "V.",
                "lastName": "Ntinas"
            },
            {
                "id": 37089912182,
                "preferredName": "D. Prousalis",
                "firstName": "D.",
                "lastName": "Prousalis"
            },
            {
                "id": 860500107905592,
                "preferredName": "R. Tetzlaff",
                "firstName": "R.",
                "lastName": "Tetzlaff"
            },
            {
                "id": 711949853664049,
                "preferredName": "S. Menzel",
                "firstName": "S.",
                "lastName": "Menzel"
            },
            {
                "id": 178628794452061,
                "preferredName": "V. Rana",
                "firstName": "V.",
                "lastName": "Rana"
            },
            {
                "id": 37283522200,
                "preferredName": "S. Nikolaidis",
                "firstName": "S.",
                "lastName": "Nikolaidis"
            },
            {
                "id": 733733104559768,
                "preferredName": "L. Chua",
                "firstName": "L.",
                "lastName": "Chua"
            }
        ]
    },
    {
        "publicationNumber": "10651575",
        "doi": "10.1109/CNNA60945.2023.10652681",
        "publicationYear": "2023",
        "publicationDate": "28-30 Sept. 2023",
        "articleNumber": "10652681",
        "articleTitle": "Memristor Applications: Nanodevices Redefining Technological Landscapes",
        "volume": null,
        "issue": null,
        "startPage": "1",
        "endPage": "5",
        "publisher": "IEEE",
        "articleContentType": "Conferences",
        "publicationTitle": "2023 18th International Workshop on Cellular Nanoscale Networks and their Applications (CNNA)",
        "authors": [
            {
                "id": 37085545768,
                "preferredName": "Nikolaos Vasileiadis",
                "firstName": "Nikolaos",
                "lastName": "Vasileiadis"
            },
            {
                "id": 37304018300,
                "preferredName": "Georgios Ch. Sirakoulis",
                "firstName": "Georgios Ch.",
                "lastName": "Sirakoulis"
            },
            {
                "id": 37318136500,
                "preferredName": "Panagiotis Dimitrakis",
                "firstName": "Panagiotis",
                "lastName": "Dimitrakis"
            }
        ]
    },
    {
        "publicationNumber": "10651575",
        "doi": "10.1109/CNNA60945.2023.10652802",
        "publicationYear": "2023",
        "publicationDate": "28-30 Sept. 2023",
        "articleNumber": "10652802",
        "articleTitle": "A Bio-Inspired Elderly Action Recognition System for Ambient Assisted Living",
        "volume": null,
        "issue": null,
        "startPage": "1",
        "endPage": "6",
        "publisher": "IEEE",
        "articleContentType": "Conferences",
        "publicationTitle": "2023 18th International Workshop on Cellular Nanoscale Networks and their Applications (CNNA)",
        "authors": [
            {
                "id": 37089454827,
                "preferredName": "Katerina Maria Oikonomou",
                "firstName": "Katerina Maria",
                "lastName": "Oikonomou"
            },
            {
                "id": 37088760414,
                "preferredName": "Ioannis Kansizoglou",
                "firstName": "Ioannis",
                "lastName": "Kansizoglou"
            },
            {
                "id": 37088524584,
                "preferredName": "Ioannis Tsampikos Papapetros",
                "firstName": "Ioannis Tsampikos",
                "lastName": "Papapetros"
            },
            {
                "id": 37303793300,
                "preferredName": "Antonios Gasteratos",
                "firstName": "Antonios",
                "lastName": "Gasteratos"
            }
        ]
    },
    {
        "publicationNumber": "10651575",
        "doi": "10.1109/CNNA60945.2023.10652837",
        "publicationYear": "2023",
        "publicationDate": "28-30 Sept. 2023",
        "articleNumber": "10652837",
        "articleTitle": "Copyright Page",
        "volume": null,
        "issue": null,
        "startPage": "1",
        "endPage": "1",
        "publisher": "IEEE",
        "articleContentType": "Conferences",
        "publicationTitle": "2023 18th International Workshop on Cellular Nanoscale Networks and their Applications (CNNA)",
        "authors": []
    },
    {
        "publicationNumber": "10651575",
        "doi": "10.1109/CNNA60945.2023.10652737",
        "publicationYear": "2023",
        "publicationDate": "28-30 Sept. 2023",
        "articleNumber": "10652737",
        "articleTitle": "Cover Page",
        "volume": null,
        "issue": null,
        "startPage": "1",
        "endPage": "1",
        "publisher": "IEEE",
        "articleContentType": "Conferences",
        "publicationTitle": "2023 18th International Workshop on Cellular Nanoscale Networks and their Applications (CNNA)",
        "authors": []
    },
    {
        "publicationNumber": "10651575",
        "doi": "10.1109/CNNA60945.2023.10652714",
        "publicationYear": "2023",
        "publicationDate": "28-30 Sept. 2023",
        "articleNumber": "10652714",
        "articleTitle": "Author Index",
        "volume": null,
        "issue": null,
        "startPage": "1",
        "endPage": "4",
        "publisher": "IEEE",
        "articleContentType": "Conferences",
        "publicationTitle": "2023 18th International Workshop on Cellular Nanoscale Networks and their Applications (CNNA)",
        "authors": []
    },
    {
        "publicationNumber": "10651575",
        "doi": "10.1109/CNNA60945.2023.10652648",
        "publicationYear": "2023",
        "publicationDate": "28-30 Sept. 2023",
        "articleNumber": "10652648",
        "articleTitle": "Table of Contents",
        "volume": null,
        "issue": null,
        "startPage": "1",
        "endPage": "3",
        "publisher": "IEEE",
        "articleContentType": "Conferences",
        "publicationTitle": "2023 18th International Workshop on Cellular Nanoscale Networks and their Applications (CNNA)",
        "authors": []
    }
]